stix_edh/__init__.py
stix_edh/common.py
stix_edh/cyber_profile.py
stix_edh/fields.py
stix_edh/isa_markings.py
stix_edh/isa_markings_assertions.py
stix_edh/namespaces.py
stix_edh/utils.py
stix_edh/version.py
stix_edh/bindings/__init__.py
stix_edh/bindings/cyber_profile.py
stix_edh/bindings/edh_common.py
stix_edh/bindings/isa_markings.py
stix_edh/bindings/isa_markings_assertions.py
stix_edh/test/__init__.py
stix_edh/test/cyber_profile_test.py
stix_edh/test/isa_markings_assertions_test.py
stix_edh/test/isa_markings_test.py
stix_edh/test/nmtokens_test.py
stix_edh/test/parsing_test.py
stix_edh-1.0.3.dist-info/LICENSE.txt
stix_edh-1.0.3.dist-info/METADATA
stix_edh-1.0.3.dist-info/WHEEL
stix_edh-1.0.3.dist-info/top_level.txt
stix_edh-1.0.3.dist-info/RECORD
