Metadata-Version: 2.1
Name: stix-edh
Version: 1.0.3
Summary: An EDH marking extension API for python-stix.
Home-page: http://stix.mitre.org
Author: The MITRE Corporation
Author-email: stix@mitre.org
License: UNKNOWN
Platform: UNKNOWN
Classifier: Development Status :: 5 - Production/Stable
Classifier: Intended Audience :: Developers
Classifier: License :: OSI Approved :: BSD License
Classifier: Operating System :: OS Independent
Classifier: Programming Language :: Python :: 3
Classifier: Programming Language :: Python :: 3.7
Classifier: Programming Language :: Python :: 3.8
Classifier: Programming Language :: Python :: 3.9
Classifier: Programming Language :: Python :: 3.10
License-File: LICENSE.txt
Requires-Dist: stix (<1.2.1.0,>=1.1.1.8)
Requires-Dist: mixbox (>=1.0.5)
